qa_transformers/__init__.py
qa_transformers/trainer.py
qa_transformers-0.1.dist-info/METADATA
qa_transformers-0.1.dist-info/WHEEL
qa_transformers-0.1.dist-info/top_level.txt
qa_transformers-0.1.dist-info/RECORD
