Metadata-Version: 2.4
Name: qa_transformers
Version: 0.1
Summary: Train QA model with feedback using Optuna and SimpleTransformers
Author: Your Name
Author-email: you@example.com
Requires-Python: >=3.8
Requires-Dist: simpletransformers>=0.63.9
Requires-Dist: optuna>=3.0.0
Dynamic: author
Dynamic: author-email
Dynamic: description
Dynamic: description-content-type
Dynamic: requires-dist
Dynamic: requires-python
Dynamic: summary
